QGISLibrary/QGISCore.py
QGISLibrary/QGISMap.py
QGISLibrary/__init__.py
qgislibrary-1.7.9.dist-info/METADATA
qgislibrary-1.7.9.dist-info/WHEEL
qgislibrary-1.7.9.dist-info/top_level.txt
qgislibrary-1.7.9.dist-info/RECORD
