Metadata-Version: 2.4
Name: QGISLibrary
Version: 1.7.9
Summary: A library based on Robot Framework for QGIS UI Automation and Testing
Author-email: Michal Pilarski <michpil@gmail.com>
License: MIT - free and open-source licence
Project-URL: Homepage, https://gitlab.com/michpil/qgis_library
Keywords: qgis,robotframework,ui automation,ui testing,pywinauto,pyautogui
Classifier: Framework :: Robot Framework
Classifier: Programming Language :: Python :: 3
Classifier: License :: OSI Approved :: MIT License
Classifier: Operating System :: OS Independent
Classifier: Topic :: Software Development :: Testing
Requires-Python: >=3.8
Requires-Dist: robotframework>=7.3.2
Requires-Dist: pywinauto>=0.6.9
Requires-Dist: PyAutoGUI>=0.9.54
Requires-Dist: pillow>=11.3.0
